MEDiml/__init__.py
MEDiml/biomarkers/__init__.py
MEDiml/biomarkers/BatchExtractor.py
MEDiml/biomarkers/BatchExtractorTexturalFilters.py
MEDiml/biomarkers/diagnostics.py
MEDiml/biomarkers/get_oriented_bound_box.py
MEDiml/biomarkers/glcm.py
MEDiml/biomarkers/gldzm.py
MEDiml/biomarkers/glrlm.py
MEDiml/biomarkers/glszm.py
MEDiml/biomarkers/int_vol_hist.py
MEDiml/biomarkers/intensity_histogram.py
MEDiml/biomarkers/local_intensity.py
MEDiml/biomarkers/morph.py
MEDiml/biomarkers/ngldm.py
MEDiml/biomarkers/ngtdm.py
MEDiml/biomarkers/stats.py
MEDiml/biomarkers/utils.py
MEDiml/filters/__init__.py
MEDiml/filters/apply_filter.py
MEDiml/filters/gabor.py
MEDiml/filters/laws.py
MEDiml/filters/log.py
MEDiml/filters/mean.py
MEDiml/filters/textural_filters_kernels.py
MEDiml/filters/TexturalFilter.py
MEDiml/filters/utils.py
MEDiml/filters/wavelet.py
MEDiml/learning/__init__.py
MEDiml/learning/cleaning_utils.py
MEDiml/learning/DataCleaner.py
MEDiml/learning/DesignExperiment.py
MEDiml/learning/FSR.py
MEDiml/learning/ml_utils.py
MEDiml/learning/Normalization.py
MEDiml/learning/RadiomicsLearner.py
MEDiml/learning/Results.py
MEDiml/learning/Stats.py
MEDiml/MEDscan.py
MEDiml/processing/__init__.py
MEDiml/processing/compute_suv_map.py
MEDiml/processing/discretisation.py
MEDiml/processing/interpolation.py
MEDiml/processing/resegmentation.py
MEDiml/processing/segmentation.py
MEDiml/utils/__init__.py
MEDiml/utils/batch_patients.py
MEDiml/utils/create_radiomics_table.py
MEDiml/utils/data_frame_export.py
MEDiml/utils/find_process_names.py
MEDiml/utils/get_file_paths.py
MEDiml/utils/get_full_rad_names.py
MEDiml/utils/get_institutions_from_ids.py
MEDiml/utils/get_patient_id_from_scan_name.py
MEDiml/utils/get_patient_names.py
MEDiml/utils/get_radiomic_names.py
MEDiml/utils/get_scan_name_from_rad_name.py
MEDiml/utils/image_reader_SITK.py
MEDiml/utils/image_volume_obj.py
MEDiml/utils/imref.py
MEDiml/utils/initialize_features_names.py
MEDiml/utils/inpolygon.py
MEDiml/utils/interp3.py
mediml-0.9.9.dist-info/LICENSE.md
mediml-0.9.9.dist-info/WHEEL
mediml-0.9.9.dist-info/METADATA
mediml-0.9.9.dist-info/RECORD
