Metadata-Version: 2.1
Name: mediml
Version: 0.9.9
Summary: MEDiml is a Python package for processing and extracting features from medical images
Home-page: https://mediml.app/
License: GPL-3.0
Keywords: python,ibsi,medical-imaging,cancer-imaging-research,radiomics,medical-image-analysis,features-extraction,radiomics-extraction,radiomics-features,radiomics-analysis
Author: MEDomics Consortium
Author-email: medomics.info@gmail.com
Requires-Python: >=3.8.0,<=3.10
Classifier: License :: OSI Approved :: GNU General Public License v3 (GPLv3)
Classifier: Programming Language :: Python :: 3
Classifier: Programming Language :: Python :: 3.10
Classifier: Programming Language :: Python :: 3.8
Classifier: Programming Language :: Python :: 3.9
Requires-Dist: Pillow
Requires-Dist: PyWavelets
Requires-Dist: SimpleITK
Requires-Dist: Sphinx
Requires-Dist: ipykernel
Requires-Dist: ipywidgets
Requires-Dist: isort
Requires-Dist: jupyter
Requires-Dist: matplotlib
Requires-Dist: networkx
Requires-Dist: neuroCombat
Requires-Dist: nibabel
Requires-Dist: nilearn
Requires-Dist: numpy
Requires-Dist: numpyencoder
Requires-Dist: pandas (<2.0.0)
Requires-Dist: protobuf
Requires-Dist: pycaret
Requires-Dist: pydicom
Requires-Dist: ray[default]
Requires-Dist: scikit_image
Requires-Dist: scikit_learn
Requires-Dist: scipy
Requires-Dist: seaborn
Requires-Dist: setuptools
Requires-Dist: sphinx-carousel (==1.2.0)
Requires-Dist: sphinx-jsonschema (==1.19.1)
Requires-Dist: sphinx-rtd-dark-mode (==1.2.4)
Requires-Dist: tabulate
Requires-Dist: tqdm
Requires-Dist: wget
Requires-Dist: xgboost
Project-URL: Bug Tracker, https://github.com/MEDomicsLab/MEDiml/issues
Project-URL: Documentation, https://mediml.readthedocs.io/
Project-URL: Repository, https://github.com/MEDomicsLab/MEDiml/
